{
    "name": "Document Manager",
    "version": "2.0.3",
    "description": "Production-ready document management plugin with secure JWT authentication, optimized memory operations, and comprehensive web interface.Go to /custom/documents.",
    "author_name": "NuvolaProject",
    "author_url": "https://nuvolaproject.cloud",
    "plugin_url": "https://github.com/mc9625/ccat_document_manager",
    "tags": "cat, documents, management, memory, rabbit hole, admin",
    "thumb": "https://raw.githubusercontent.com/mc9625/ccat_document_manager/main/ccat_document_manager.png"
}
